lib/routingblocks.lib
routingblocks/__init__.py
routingblocks/_routingblocks.cp38-win_amd64.pyd
routingblocks/_routingblocks.pyi
routingblocks/adptw/__init__.py
routingblocks/include/dynamic_bitset/dynamic_bitset.hpp
routingblocks/include/dynamic_bitset/libpopcnt.h
routingblocks/include/routingblocks/adaptive_large_neighborhood.hpp
routingblocks/include/routingblocks/ADPTWEvaluation.h
routingblocks/include/routingblocks/arc.h
routingblocks/include/routingblocks/binding_helpers.hpp
routingblocks/include/routingblocks/evaluation.h
routingblocks/include/routingblocks/FRVCP.h
routingblocks/include/routingblocks/insertion_cache.h
routingblocks/include/routingblocks/Instance.h
routingblocks/include/routingblocks/lns_operators.h
routingblocks/include/routingblocks/LocalSearch.h
routingblocks/include/routingblocks/NIFTWEvaluation.h
routingblocks/include/routingblocks/node.h
routingblocks/include/routingblocks/operators/InsertStationOperator.h
routingblocks/include/routingblocks/operators/InterRouteTwoOptOperator.h
routingblocks/include/routingblocks/operators/RemoveStationOperator.h
routingblocks/include/routingblocks/operators/SwapOperator.h
routingblocks/include/routingblocks/operators.h
routingblocks/include/routingblocks/removal_cache.h
routingblocks/include/routingblocks/Solution.h
routingblocks/include/routingblocks/types.h
routingblocks/include/routingblocks/utility/adaptive_priority_list.h
routingblocks/include/routingblocks/utility/algorithms.h
routingblocks/include/routingblocks/utility/arc_set.h
routingblocks/include/routingblocks/utility/heap.h
routingblocks/include/routingblocks/utility/iterator_pair.h
routingblocks/include/routingblocks/utility/random.h
routingblocks/include/routingblocks/vertex.h
routingblocks/include/small_vector/small_vector.hpp
routingblocks/include/xoshiro/xoshiro.h
routingblocks/large_neighborhood.py
routingblocks/niftw/__init__.py
routingblocks/operators/__init__.py
routingblocks/operators/best_insert.py
routingblocks-0.2.1.dist-info/METADATA
routingblocks-0.2.1.dist-info/WHEEL
routingblocks-0.2.1.dist-info/entry_points.txt
routingblocks-0.2.1.dist-info/RECORD
