Metadata-Version: 2.1
Name: routingblocks
Version: 0.2.1
Summary: A package for the implementation of vehicle routing problems with intermediate stops
Author-Email: Patrick Sean Klein <patrick.sean.klein@tum.de>
Classifier: Development Status :: 4 - Beta
Classifier: License :: OSI Approved :: MIT License
Classifier: Programming Language :: Python :: 3 :: Only
Classifier: Programming Language :: Python :: 3.8
Classifier: Programming Language :: Python :: 3.9
Classifier: Programming Language :: Python :: 3.10
Classifier: Programming Language :: Python :: 3.11
Requires-Python: >=3.8
Provides-Extra: test
Provides-Extra: docs
Provides-Extra: examples
Requires-Dist: pytest; extra == "test"
Requires-Dist: pytest-benchmark; extra == "test"
Requires-Dist: pytest-randomly; extra == "test"
Requires-Dist: pytest-cov; extra == "test"
Requires-Dist: pydantic; extra == "test"
Requires-Dist: sphinx; extra == "docs"
Requires-Dist: sphinx-rtd-theme; extra == "docs"
Requires-Dist: sphinx-autodoc-typehints; extra == "docs"
Requires-Dist: sphinx-autoapi; extra == "docs"
Requires-Dist: sphinxcontrib-bibtex; extra == "docs"
Requires-Dist: sphinxcontrib-mermaid; extra == "docs"
Requires-Dist: click; extra == "examples"
Requires-Dist: pydantic; extra == "examples"
